[
  {
    "title": "Today's Surprising Recall Data",
    "date": "2026-04-04",
    "category": "daily-digest",
    "brands": [
      "Made Fresh Salads Inc",
      "Willamette Valley Pie Company, LLC",
      "CNC Noodle Corporation",
      "Cocos Wholesale and Imports, LLC",
      "House Of Flavors, Inc."
    ],
    "severity": "Class I",
    "tldr": "As of today, April 4, 2026, there have been a staggering 222 food recalls this year alone. Among these, 71 have been classified as Class I recalls, which means they pose a significant risk to health. ",
    "slug": "2026-04-04-daily-digest"
  }
]